setup.cfg
setup.py
dataflux/__init__.py
dataflux/array.py
dataflux/number.py
dataflux.egg-info/PKG-INFO
dataflux.egg-info/SOURCES.txt
dataflux.egg-info/dependency_links.txt
dataflux.egg-info/not-zip-safe
dataflux.egg-info/requires.txt
dataflux.egg-info/top_level.txt