Metadata-Version: 1.0
Name: dataflux
Version: 0.1.1
Summary: DataScience Package
Home-page: UNKNOWN
Author: UNKNOWN
Author-email: UNKNOWN
License: UNKNOWN
Platform: UNKNOWN
